{
  "question": "Uvažujte bezkontextovou gramatiku $G = (N, \\Sigma, P, S)$. O každém z následujících tvrzení rozhodněte, zdali je pravdivé či nepravdivé:",
  "question_type": "multichoice",
  "answers": [
    {
      "text": "Terminál $x \\in \\Sigma$ je nedostupný v $G$ právě tehdy, když neexistuje derivace $S \\Rightarrow^* \\alpha x \\beta$, kde $\\alpha, \\beta \\in (N \\cup \\Sigma)^*$.",
      "is_correct": true
    },
    {
      "text": "Neterminál $X \\in N$ je nedostupný v $G$ právě tehdy, když neexistuje derivace $S \\Rightarrow^* \\alpha X \\beta$, kde $\\alpha, \\beta \\in (N \\cup \\Sigma)^*$.",
      "is_correct": true
    },
    {
      "text": "Symbol $X$ je nedostupný právě tehdy, když je zbytečný.",
      "is_correct": false
    },
    {
      "text": "$S$ je vždy dostupný symbol.",
      "is_correct": true
    }
  ]
}