{
    "question": "Mějme následující regulární výraz $V$ nad abecedou $\\{a, b, c\\}$:\n\n$$V = (a(\\emptyset^* + b) + cb^*)^* c^*$$\n\nKolik KONCOVÝCH stavů bude mít konečný automat $M$, který vznikne použitím algoritmu pro konstrukci NKA pro daný regulární výraz – metody sousedů (Glushkov)? Uvažujte použití algoritmu na $V$ v zadaném tvaru bez úprav $V$ nebo vzniklého $M$. (Zadávejte pouze celé číslo v desítkové soustavě pomocí číslic bez zbytečných úvodních nul.)",
    "answers": [
        {
            "text": "6",
            "isCorrect": true
        }
    ],
    "topics": [
        "regularni-jazyky"
    ],
    "questionType": "open"
}