{
    "question": "Pro Myhill-Nerodovu větu platí:",
    "answers": [
        {
            "text": "popisuje jednu vlastnost regulárních gramatik",
            "isCorrect": true
        },
        {
            "text": "dokazuje, že je jazyk bezkontextový",
            "isCorrect": false
        },
        {
            "text": "dokazuje, že jazyk není regulární",
            "isCorrect": true
        },
        {
            "text": "dokazuje, že jazyk je regulární",
            "isCorrect": true
        }
    ],
    "topics": [
        "regularni-jazyky",
        "google-doc"
    ],
    "questionType": "multichoice",
    "originalText": "113) Pro Myhill-Nerodovu větu platí:\na) popisuje 1 vlastnost regulární gr.\nb) dokazuje, že je jazyk bezkontextový\nc) dokazuje, že jazyk není regulární\nd) dokazuje, že jazyk je regulární\nA,C,D     ."
}